dspw/mpb/__init__.py
dspw/mpb/source_protocol.py
dspw/mpb/serializers/__init__.py
dspw/mpb/serializers/kafka.py
dspw/mpb/serializers/nats.py
dspw/mpb/serializers/utils.py
dspw/schema/__init__.py
dspw/schema/news_event.py
dspw-0.2.7.dist-info/METADATA
dspw-0.2.7.dist-info/WHEEL
dspw-0.2.7.dist-info/top_level.txt
dspw-0.2.7.dist-info/RECORD
