Metadata-Version: 2.4
Name: dspw
Version: 0.2.7
Summary: Data Stream Protocol Wire. A Python library that provides a unified message protocol baseline (MPB) and transport abstraction for ingesting, normalizing, and redistributing financial or journalistic content from heterogeneous online sources
Author-email: Lance M <lance.mk@bitstric.com>
License: MIT
Project-URL: Homepage, https://bitbucket.org/xft-software/dspw
Project-URL: Repository, https://bitbucket.org/xft-software/dspw
Project-URL: Issues, https://bitbucket.org/xft-software/dspw/issues
Keywords: news,message-broker,kafka,nats,event-driven,pubsub,news-ingestion,data-pipeline,real-time-analytics,source-metadata,serialization,schema-normalization,quant-research,feed-parser,python-library,distribution
Requires-Python: >=3.9
Requires-Dist: pydantic>=2.0
Requires-Dist: confluent-kafka>=2.3.0
Requires-Dist: nats-py>=2.7.0
